anger.py
angerr-0.0.5.dist-info/LICENSE.txt
angerr-0.0.5.dist-info/METADATA
angerr-0.0.5.dist-info/WHEEL
angerr-0.0.5.dist-info/top_level.txt
angerr-0.0.5.dist-info/RECORD
