Metadata-Version: 2.1
Name: angerr
Version: 0.0.5
Summary: When your coding doesn't work, simply call the rage function with the amount of your rage and you will feel much, much better.
Home-page: https://github.com/MasterCoder21/anger
Author: minecraftpr03
License: UNKNOWN
Platform: UNKNOWN
Classifier: Programming Language :: Python :: 3
Classifier: Programming Language :: Python :: 3.6
Classifier: Programming Language :: Python :: 3.7
Classifier: Programming Language :: Python :: 3.8
Classifier: Programming Language :: Python :: 3.9
Classifier: License :: OSI Approved :: MIT License
Classifier: Operating System :: OS Independent
